pyautogui_simplified_edition/__init__.py
pyautogui_simplified_edition/screen.py
pyautogui_simplified_edition-1.0a2.dist-info/METADATA
pyautogui_simplified_edition-1.0a2.dist-info/WHEEL
pyautogui_simplified_edition-1.0a2.dist-info/top_level.txt
pyautogui_simplified_edition-1.0a2.dist-info/RECORD
