Metadata-Version: 2.1
Name: pyautogui_simplified_edition
Version: 1.0a2
Summary: A simplified edition of the PyAutoGUI library
Author: Жужелица
Project-URL: Homepage, https://github.com/immacool/pyautogui-simplified-edition
Project-URL: Bug Tracker, https://github.com/immacool/pyautogui-simplified-edition/issues
Classifier: Programming Language :: Python :: 3
Classifier: Programming Language :: Python :: 3.6
Classifier: Programming Language :: Python :: 3.7
Classifier: Programming Language :: Python :: 3.8
Classifier: Programming Language :: Python :: 3.9
Classifier: Operating System :: OS Independent
Requires-Python: >=3.6
